bayesnest/__init__.py
bayesnest/priors.py
bayesnest/sampler.py
bayesnest/utils.py
bayesnest-1.0.0.dist-info/METADATA
bayesnest-1.0.0.dist-info/WHEEL
bayesnest-1.0.0.dist-info/top_level.txt
bayesnest-1.0.0.dist-info/RECORD
